<?xml version="1.0" encoding="UTF-8"?>
<vocabulary primary="ENG">
    <sentence mode="on" keyword="all_applications">
        <entry lang="RUS">Все заявки</entry>
        <entry lang="ENG">All applications</entry>
        <entry lang="KAZ">Барлық өтінімдер</entry>
    </sentence>
    <sentence mode="on" keyword="my_applications">
        <entry lang="RUS">Мои заявки</entry>
        <entry lang="ENG">My applications</entry>
        <entry lang="KAZ">Менің өтінімдерім</entry>
    </sentence>

    <sentence mode="on" keyword="applications_for_vehicle">
        <entry lang="RUS">Заявки на транспорт</entry>
        <entry lang="ENG">Applications for vehicle</entry>
        <entry lang="KAZ">Көлік құралына арналған өтініштер</entry>
    </sentence>
    <sentence mode="on" keyword="application_for_vehicle">
        <entry lang="RUS">Заявка на транспорт</entry>
        <entry lang="ENG">Application for vehicle</entry>
        <entry lang="KAZ">Көлік құралына арналған өтініш</entry>
    </sentence>
    <sentence mode="on" keyword="applicationforvehicle">
        <entry lang="RUS">Заявка на транспорт</entry>
        <entry lang="ENG">Application for vehicle</entry>
        <entry lang="KAZ">Көлік құралына арналған өтініш</entry>
    </sentence>

    <sentence mode="on" keyword="start_date">
        <entry lang="RUS">Дата начала</entry>
        <entry lang="ENG">Start date</entry>
        <entry lang="KAZ">Басталуы</entry>
    </sentence>
    <sentence mode="on" keyword="due_date">
        <entry lang="RUS">Срок исполнения</entry>
        <entry lang="ENG">Due date</entry>
        <entry lang="POR">Data de vencimento</entry>
        <entry lang="SPA">Fecha de finalización</entry>
    </sentence>

    <sentence mode="on" keyword="vehicle">
        <entry lang="RUS">Транспортное средство</entry>
        <entry lang="ENG">Vehicle</entry>
        <entry lang="KAZ">Көлік</entry>
    </sentence>
    <sentence mode="on" keyword="use_from">
        <entry lang="RUS">От</entry>
        <entry lang="ENG">From</entry>
        <entry lang="KAZ">Басталуы</entry>
    </sentence>
    <sentence mode="on" keyword="use_to">
        <entry lang="RUS">До</entry>
        <entry lang="ENG">Until</entry>
        <entry lang="KAZ">Дейін</entry>
    </sentence>
    <sentence mode="on" keyword="route">
        <entry lang="RUS">Маршрут</entry>
        <entry lang="ENG">Route</entry>
        <entry lang="KAZ">Бағыт</entry>
    </sentence>
</vocabulary>
